README.md
setup.cfg
setup.py
src/ss_concurrent_log_handler.egg-info/PKG-INFO
src/ss_concurrent_log_handler.egg-info/SOURCES.txt
src/ss_concurrent_log_handler.egg-info/dependency_links.txt
src/ss_concurrent_log_handler.egg-info/not-zip-safe
src/ss_concurrent_log_handler.egg-info/requires.txt
src/ss_concurrent_log_handler.egg-info/top_level.txt
src/ssc_concurrent_log_handler/__init__.py
src/ssc_concurrent_log_handler/__version__.py